<?xml version="1.0" encoding="UTF-8"?>
<actions>
<action>
	<icon>utilities-terminal</icon>
	<name>Open Terminal Here</name>
	<submenu></submenu>
	<unique-id>1690237560590634-1</unique-id>
	<command>exo-open --working-directory %f --launch TerminalEmulator</command>
	<description>Example for a custom action</description>
	<range></range>
	<patterns>*</patterns>
	<startup-notify/>
	<directories/>
</action>
<action>
	<icon>org.gnome.Meld</icon>
	<name>Compare</name>
	<submenu></submenu>
	<unique-id>1693256858082832-1</unique-id>
	<command>meld %F</command>
	<description></description>
	<range>*</range>
	<patterns>*</patterns>
	<directories/>
	<other-files/>
	<text-files/>
</action>
</actions>
